MANIFEST.in
README.md
README.zh-CN.md
requirements.txt
setup.py
keras_embed_sim/__init__.py
keras_embed_sim/embeddings.py
keras_embed_sim.egg-info/PKG-INFO
keras_embed_sim.egg-info/SOURCES.txt
keras_embed_sim.egg-info/dependency_links.txt
keras_embed_sim.egg-info/requires.txt
keras_embed_sim.egg-info/top_level.txt
tests/__init__.py
tests/test_embeddings.py