Metadata-Version: 2.1
Name: keras-embed-sim
Version: 0.10.0
Summary: Calculate similarity with embedding
Home-page: https://github.com/CyberZHG/keras-embed-sim
Author: CyberZHG
Author-email: CyberZHG@users.noreply.github.com
License: MIT
Platform: UNKNOWN
Classifier: Programming Language :: Python :: 3
Classifier: License :: OSI Approved :: MIT License
Classifier: Operating System :: OS Independent
